mega_downloader.py
mega_lite-2.0.0.dist-info/licenses/LICENSE
mega_lite-2.0.0.dist-info/METADATA
mega_lite-2.0.0.dist-info/WHEEL
mega_lite-2.0.0.dist-info/entry_points.txt
mega_lite-2.0.0.dist-info/top_level.txt
mega_lite-2.0.0.dist-info/RECORD
